beetsplug/__init__.py
beetsplug/importmodifyinfo/__init__.py
beetsplug/importmodifyinfo/plugin.py
beetsplug/importmodifyinfo/py.typed
beets_importmodifyinfo-0.9.0.dist-info/LICENSE
beets_importmodifyinfo-0.9.0.dist-info/METADATA
beets_importmodifyinfo-0.9.0.dist-info/WHEEL
beets_importmodifyinfo-0.9.0.dist-info/RECORD
